{
  "payees": [
    {
      "_notes": "Payee nicholas@intrinsik.ly",
      "email": "nicholas@intrinsik.ly",
      "password": "Dem0is!123",
      "id": "6490269e40ccc302e938166a",
      "businessId": "649026f440ccc302e9381684",
      "userToken": "tokenhere"
    }
  ],
  "customerDetails": {
    "firstName": "Cypress",
    "lastName": "Script",
    "phoneNumber": "123456789",
    "officeNumber": "123456789",
    "userType": "individual",
    "bizName": "Cy Biz",
    "shortName": "CyBiz",
    "addressLine1": "Running",
    "addressLine2": "Scripted",
    "city": "Test",
    "state": "KL",
    "postcode": "55100",
    "countryCode": "MY"
  },
  "customers": [
    {
      "_notes": "1st customer created",
      "ref": "4.7.23",
      "email": "intrinsiktest+1.1688104268@gmail.com",
      "id": "649e6d4c49dbb8a1152d712f",
      "invoice": "649e991d9e892f3eb0a6f894",
      "lod": ""
    },
    {
      "_notes": "2nd customer created",
      "email": "intrinsiktest+2.1688104268@gmail.com",
      "id": "649e6d4c49dbb8a1152d7142",
      "invoice": "649e991d9e892f3eb0a6f894",
      "lod": ""
    },
    {
      "_notes": "3rd customer created",
      "email": "intrinsiktest+2.1688104268@gmail.com",
      "id": "649e6d4c49dbb8a1152d7142",
      "invoice": "649e991d9e892f3eb0a6f894",
      "lod": ""
    },
    {
      "_notes": "4th customer created",
      "email": "intrinsiktest+2.1688104268@gmail.com",
      "id": "649e6d4c49dbb8a1152d7142",
      "invoice": "649e991d9e892f3eb0a6f894",
      "lod": ""
    },
    {
      "_notes": "5th customer created",
      "email": "intrinsiktest+2.1688104268@gmail.com",
      "id": "649e6d4c49dbb8a1152d7142",
      "invoice": "649e991d9e892f3eb0a6f894",
      "lod": ""
    },
    {
      "_notes": "6th customer created",
      "email": "intrinsiktest+2.1688104268@gmail.com",
      "id": "649e6d4c49dbb8a1152d7142",
      "invoice": "649e991d9e892f3eb0a6f894",
      "lod": ""
    },
    {
      "_notes": "7th customer created",
      "email": "intrinsiktest+2.1688104268@gmail.com",
      "id": "649e6d4c49dbb8a1152d7142",
      "invoice": "649e991d9e892f3eb0a6f894",
      "lod": ""
    },
    {
      "_notes": "8th customer created",
      "email": "intrinsiktest+2.1688104268@gmail.com",
      "id": "649e6d4c49dbb8a1152d7142",
      "invoice": "649e991d9e892f3eb0a6f894",
      "lod": ""
    },
    {
      "_notes": "9th customer created",
      "email": "intrinsiktest+2.1688104268@gmail.com",
      "id": "649e6d4c49dbb8a1152d7142",
      "invoice": "649e991d9e892f3eb0a6f894",
      "lod": ""
    },
    {
      "_notes": "10th customer created",
      "email": "intrinsiktest+2.1688104268@gmail.com",
      "id": "649e6d4c49dbb8a1152d7142",
      "invoice": "649e991d9e892f3eb0a6f894",
      "lod": ""
    },
    {
      "_notes": "11th customer created",
      "email": "intrinsiktest+2.1688104268@gmail.com",
      "id": "649e6d4c49dbb8a1152d7142",
      "invoice": "649e991d9e892f3eb0a6f894",
      "lod": ""
    },
    {
      "_notes": "12th customer created",
      "email": "intrinsiktest+2.1688104268@gmail.com",
      "id": "649e6d4c49dbb8a1152d7142",
      "invoice": "649e991d9e892f3eb0a6f894",
      "lod": ""
    },
    {
      "_notes": "13th customer created",
      "email": "intrinsiktest+2.1688104268@gmail.com",
      "id": "649e6d4c49dbb8a1152d7142",
      "invoice": "649e991d9e892f3eb0a6f894",
      "lod": ""
    },
    {
      "_notes": "14th customer created",
      "email": "intrinsiktest+2.1688104268@gmail.com",
      "id": "649e6d4c49dbb8a1152d7142",
      "invoice": "649e991d9e892f3eb0a6f894",
      "lod": ""
    },
    {
      "_notes": "15th customer created",
      "email": "intrinsiktest+2.1688104268@gmail.com",
      "id": "649e6d4c49dbb8a1152d7142",
      "invoice": "649e991d9e892f3eb0a6f894",
      "lod": ""
    },
    {
      "_notes": "16th customer created",
      "email": "intrinsiktest+2.1688104268@gmail.com",
      "id": "649e6d4c49dbb8a1152d7142",
      "invoice": "649e991d9e892f3eb0a6f894",
      "lod": ""
    },
    {
      "_notes": "17th customer created",
      "email": "intrinsiktest+2.1688104268@gmail.com",
      "id": "649e6d4c49dbb8a1152d7142",
      "invoice": "649e991d9e892f3eb0a6f894",
      "lod": ""
    },
    {
      "_notes": "18th customer created",
      "email": "intrinsiktest+2.1688104268@gmail.com",
      "id": "649e6d4c49dbb8a1152d7142",
      "invoice": "649e991d9e892f3eb0a6f894",
      "lod": ""
    },
    {
      "_notes": "19th customer created",
      "email": "intrinsiktest+2.1688104268@gmail.com",
      "id": "649e6d4c49dbb8a1152d7142",
      "invoice": "649e991d9e892f3eb0a6f894",
      "lod": ""
    },
    {
      "_notes": "20th customer created",
      "email": "intrinsiktest+2.1688104268@gmail.com",
      "id": "649e6d4c49dbb8a1152d7142",
      "invoice": "649e991d9e892f3eb0a6f894",
      "lod": ""
    }
  ]
}